fns/__init__.py
fns/functions.py
dsfns-3.0.dist-info/METADATA
dsfns-3.0.dist-info/WHEEL
dsfns-3.0.dist-info/top_level.txt
dsfns-3.0.dist-info/RECORD
