Metadata-Version: 2.1
Name: dsfns
Version: 3.0
Summary: data Preprocessing fns
Home-page: https://github.com/zeta9097/fns
Author: Mafia
Author-email: zeta9097@gmail.com
Classifier: Programming Language :: Python :: 3
Classifier: License :: OSI Approved :: MIT License
Classifier: Operating System :: OS Independent
Requires-Python: >=3.6
